st_oxview/.DS_Store
st_oxview/__init__.py
st_oxview/index.html
st_oxview/__pycache__/__init__.cpython-312.pyc
st_oxview/oxview_src/.DS_Store
st_oxview/oxview_src/favicon.png
st_oxview/oxview_src/index.html
st_oxview/oxview_src/index.js
st_oxview/oxview_src/renderer.js
st_oxview/oxview_src/css/justcontext.css
st_oxview/oxview_src/css/metro-colors.min.css
st_oxview/oxview_src/css/metro-icons.min.css
st_oxview/oxview_src/css/metro.min.css
st_oxview/oxview_src/css/style.css
st_oxview/oxview_src/css/style_old.css
st_oxview/oxview_src/dist/.DS_Store
st_oxview/oxview_src/dist/main.js
st_oxview/oxview_src/dist/ox-serve.js
st_oxview/oxview_src/dist/UI/UI.js
st_oxview/oxview_src/dist/UI/base_selector.js
st_oxview/oxview_src/dist/UI/keybindings.js
st_oxview/oxview_src/dist/api/editing_api.js
st_oxview/oxview_src/dist/api/live_relax.js
st_oxview/oxview_src/dist/api/observable_api.js
st_oxview/oxview_src/dist/api/plugin_api.js
st_oxview/oxview_src/dist/api/scene_api.js
st_oxview/oxview_src/dist/editing/clustering.js
st_oxview/oxview_src/dist/editing/dijkstra.js
st_oxview/oxview_src/dist/editing/distance.js
st_oxview/oxview_src/dist/editing/doUndo.js
st_oxview/oxview_src/dist/editing/editing.js
st_oxview/oxview_src/dist/editing/rigid-body_simulation.js
st_oxview/oxview_src/dist/editing/selections.js
st_oxview/oxview_src/dist/editing/sim_worker.js
st_oxview/oxview_src/dist/editing/translation.js
st_oxview/oxview_src/dist/file_handling/GLTFExporter.js
st_oxview/oxview_src/dist/file_handling/UNF_reader.js
st_oxview/oxview_src/dist/file_handling/aux_readers.js
st_oxview/oxview_src/dist/file_handling/file_getters.js
st_oxview/oxview_src/dist/file_handling/file_handling.js
st_oxview/oxview_src/dist/file_handling/handling.js
st_oxview/oxview_src/dist/file_handling/io.js
st_oxview/oxview_src/dist/file_handling/order_parameter_selector.js
st_oxview/oxview_src/dist/file_handling/output_file.js
st_oxview/oxview_src/dist/file_handling/parameter_file.js
st_oxview-0.1.6.dist-info/licenses/LICENSE
st_oxview-0.1.6.dist-info/METADATA
st_oxview-0.1.6.dist-info/WHEEL
st_oxview-0.1.6.dist-info/top_level.txt
st_oxview-0.1.6.dist-info/RECORD
