Metadata-Version: 2.4
Name: st_oxview
Version: 0.1.6
Summary: A Streamlit component for coarse-grained DNA/RNA visualization with OxView
Home-page: https://github.com/Lucandia/st_oxview
Author: Luca Monari
Author-email: Luca.Monari@mr.mpg.de
Requires-Python: >=3.7
License-File: LICENSE
Requires-Dist: streamlit
Requires-Dist: matplotlib
Requires-Dist: IPython
Dynamic: author
Dynamic: author-email
Dynamic: description
Dynamic: description-content-type
Dynamic: home-page
Dynamic: license-file
Dynamic: requires-dist
Dynamic: requires-python
Dynamic: summary
